dependency_container/__init__.py
dependency_container/container.py
dependency_container/fastapi.py
dependency_container/py.typed
dependency_container/route.py
dependency_container/signature.py
dependency_container/faststream/__init__.py
dependency_container/faststream/nats.py
dependency_container/faststream/redis.py
dependency_container-0.3.0.dist-info/METADATA
dependency_container-0.3.0.dist-info/WHEEL
dependency_container-0.3.0.dist-info/licenses/LICENSE
dependency_container-0.3.0.dist-info/RECORD
